ncdiff/__init__.py
ncdiff/calculator.py
ncdiff/composer.py
ncdiff/config.py
ncdiff/errors.py
ncdiff/manager.py
ncdiff/model.py
ncdiff/netconf.py
ncdiff/ref.py
ncdiff/runningconfig.py
ncdiff/plugins/__init__.py
ncdiff/plugins/cxml.py
ncdiff/plugins/pyimport.py
ncdiff/tests/__init__.py
ncdiff/tests/test_ncdiff.py
ncdiff/tests/test_running_config.py
ncdiff/tests/yang/ATM-FORUM-TC-MIB.yang
ncdiff/tests/yang/ATM-MIB.yang
ncdiff/tests/yang/ATM-TC-MIB.yang
ncdiff/tests/yang/BGP4-MIB.yang
ncdiff/tests/yang/BRIDGE-MIB.yang
ncdiff/tests/yang/CISCO-AAA-SERVER-MIB.yang
ncdiff/tests/yang/CISCO-AAA-SESSION-MIB.yang
ncdiff/tests/yang/CISCO-AAL5-MIB.yang
ncdiff/tests/yang/CISCO-ATM-EXT-MIB.yang
ncdiff/tests/yang/CISCO-ATM-PVCTRAP-EXTN-MIB.yang
ncdiff/tests/yang/CISCO-ATM-QOS-MIB.yang
ncdiff/tests/yang/CISCO-BGP-POLICY-ACCOUNTING-MIB.yang
ncdiff/tests/yang/CISCO-BGP4-MIB.yang
ncdiff/tests/yang/CISCO-BULK-FILE-MIB.yang
ncdiff/tests/yang/CISCO-CBP-TARGET-MIB.yang
ncdiff/tests/yang/CISCO-CBP-TARGET-TC-MIB.yang
ncdiff/tests/yang/CISCO-CBP-TC-MIB.yang
ncdiff/tests/yang/CISCO-CDP-MIB.yang
ncdiff/tests/yang/CISCO-CEF-MIB.yang
ncdiff/tests/yang/CISCO-CEF-TC.yang
ncdiff/tests/yang/CISCO-CONFIG-COPY-MIB.yang
ncdiff/tests/yang/CISCO-CONFIG-MAN-MIB.yang
ncdiff/tests/yang/CISCO-CONTEXT-MAPPING-MIB.yang
ncdiff/tests/yang/CISCO-DATA-COLLECTION-MIB.yang
ncdiff/tests/yang/CISCO-DIAL-CONTROL-MIB.yang
ncdiff/tests/yang/CISCO-DOT3-OAM-MIB.yang
ncdiff/tests/yang/CISCO-DYNAMIC-TEMPLATE-MIB.yang
ncdiff/tests/yang/CISCO-DYNAMIC-TEMPLATE-TC-MIB.yang
ncdiff/tests/yang/CISCO-EIGRP-MIB.yang
ncdiff/tests/yang/CISCO-EMBEDDED-EVENT-MGR-MIB.yang
ncdiff/tests/yang/CISCO-ENHANCED-MEMPOOL-MIB.yang
ncdiff/tests/yang/CISCO-ENTITY-ALARM-MIB.yang
ncdiff/tests/yang/CISCO-ENTITY-EXT-MIB.yang
ncdiff/tests/yang/CISCO-ENTITY-FRU-CONTROL-MIB.yang
ncdiff/tests/yang/CISCO-ENTITY-QFP-MIB.yang
ncdiff/tests/yang/CISCO-ENTITY-SENSOR-MIB.yang
ncdiff/tests/yang/CISCO-ENTITY-VENDORTYPE-OID-MIB.yang
ncdiff-26.1.dist-info/LICENSE
ncdiff-26.1.dist-info/METADATA
ncdiff-26.1.dist-info/NOTICE
ncdiff-26.1.dist-info/WHEEL
ncdiff-26.1.dist-info/top_level.txt
ncdiff-26.1.dist-info/RECORD
